erd_mesh/__init__.py
erd_mesh/weather.py
erd_mesh-0.1.1.dist-info/METADATA
erd_mesh-0.1.1.dist-info/WHEEL
erd_mesh-0.1.1.dist-info/top_level.txt
erd_mesh-0.1.1.dist-info/RECORD
